displayhooks/__init__.py
displayhooks/autorestore.py
displayhooks/converter.py
displayhooks/not_display.py
displayhooks/py.typed
displayhooks-0.0.5.dist-info/LICENSE
displayhooks-0.0.5.dist-info/METADATA
displayhooks-0.0.5.dist-info/WHEEL
displayhooks-0.0.5.dist-info/top_level.txt
displayhooks-0.0.5.dist-info/RECORD
